eyesapp/__init__.py
eyesapp/eyesapp.py
eyesapp-0.1.0.dist-info/METADATA
eyesapp-0.1.0.dist-info/WHEEL
eyesapp-0.1.0.dist-info/RECORD
